pypbp/__init__.c
pypbp/__init__.cpython-38-darwin.so
pypbp/__init__.py
pypbp/__init__.pyx
pypbp/pypbp.py
pypbp/data/timeseries.xlsx
pypbp-0.0.11.dist-info/LICENSE
pypbp-0.0.11.dist-info/METADATA
pypbp-0.0.11.dist-info/WHEEL
pypbp-0.0.11.dist-info/dependency_links.txt
pypbp-0.0.11.dist-info/top_level.txt
pypbp-0.0.11.dist-info/RECORD
