Metadata-Version: 2.1
Name: pypbp
Version: 0.0.11
Summary: A python package for predicting insect outbreaks based on the Pattern Based Prediction method
Home-page: https://github.com/GabrielRPalma/pypbp
Author: Gabriel Rodrigues Palma
Author-email: gabrielrpalma2@gmail.com
License: MIT license
Keywords: pypbp
Classifier: Development Status :: 2 - Pre-Alpha
Classifier: Intended Audience :: Developers
Classifier: License :: OSI Approved :: MIT License
Classifier: Natural Language :: English
Classifier: Programming Language :: Python :: 3
Classifier: Programming Language :: Python :: 3.7
Classifier: Programming Language :: Python :: 3.8
Classifier: Programming Language :: Python :: 3.9
Requires-Python: >=3.7
License-File: LICENSE
Requires-Dist: numpy
Requires-Dist: sklearn
Requires-Dist: cython (==0.29.30)
Requires-Dist: scipy
Requires-Dist: pandas
Requires-Dist: emd
Requires-Dist: openpyxl
Requires-Dist: matplotlib
